LICENSE
MANIFEST.in
setup.py
previewadmin/__init__.py
previewadmin/admin.py
previewadmin/static/previewadmin/css/previewadmin.css
previewadmin/static/previewadmin/img/loader.gif
previewadmin/static/previewadmin/js/previewadmin.js
previewadmin/templates/preview_tabular_inline.html
previewadmin/templates/previewadmin_change_form.html
previewadmin/templates/previewadmin_fieldset.html
previewadmin/templatetags/__init__.py
previewadmin/templatetags/previewadmin_tags.py
twentytab_previewadmin.egg-info/PKG-INFO
twentytab_previewadmin.egg-info/SOURCES.txt
twentytab_previewadmin.egg-info/dependency_links.txt
twentytab_previewadmin.egg-info/requires.txt
twentytab_previewadmin.egg-info/top_level.txt