Metadata-Version: 1.0
Name: twentytab-previewadmin
Version: 0.5
Summary: A django app that initializes admin changelist view with a useful tool to have a preview of instances
Home-page: https://github.com/20tab/twentytab-previewadmin
Author: 20tab S.r.l.
Author-email: info@20tab.com
License: MIT License
Platform: UNKNOWN
